sysmaid/__init__.py
sysmaid/maid.py
sysmaid/action/__init__.py
sysmaid/action/alarm.py
sysmaid/action/get_top_processes.py
sysmaid/action/kill_process.py
sysmaid/action/lock_volume.py
sysmaid/action/stop_service.py
sysmaid/action/write_file.py
sysmaid/condiction/__init__.py
sysmaid/condiction/has_no_window.py
sysmaid/condiction/has_windows_look_like.py
sysmaid/condiction/is_exited.py
sysmaid/condiction/is_running.py
sysmaid/condiction/is_too_busy.py
sysmaid/i18n/__init__.py
sysmaid/i18n/en_us.py
sysmaid/i18n/zh_cn.py
sysmaid-0.7.6.dist-info/licenses/LICENSE
sysmaid-0.7.6.dist-info/METADATA
sysmaid-0.7.6.dist-info/WHEEL
sysmaid-0.7.6.dist-info/top_level.txt
sysmaid-0.7.6.dist-info/RECORD
