Metadata-Version: 2.4
Name: sysmaid
Version: 0.7.6
Summary: 为 Windows 高级用户和开发者打造：一个基于Python的系统管理框架，用于轻松发现并治理那些不守规矩的后台应用和服务。
Author-email: Tony Zhang <zhangtony239@gmail.com>
License: GPL-3.0-only
Classifier: Programming Language :: Python :: 3
Classifier: Operating System :: Microsoft :: Windows
Requires-Python: >=3.8
License-File: LICENSE
Requires-Dist: WMI
Requires-Dist: pywin32
Requires-Dist: psutil
Requires-Dist: mss
Requires-Dist: opencv-python
Provides-Extra: test
Requires-Dist: pytest; extra == "test"
Dynamic: license-file
